IPSMovement.v
`timescale 1ns / 1ps
//////////////////////////////////////////////////////////////////////////////////
// Company: 
// Engineer: 
// 
// Create Date: 11/26/2019 12:40:48 AM
// Design Name: 
// Module Name: IPSMovement
// Project Name: 
// Target Devices: 
// Tool Versions: 
// Description: 
// 
// Dependencies: 
// 
// Revision:
// Revision 0.01 - File Created
// Additional Comments:
// 
//////////////////////////////////////////////////////////////////////////////////

module IPSMovement
  (input             clk,
   input [2:0]       IPS,
   input             IR,
   input             IRModuleDone,
   output reg [3:0]  Direction,
   output reg [11:0] DutyA, DutyB,
   output reg        EnableIRModule,
   output reg        ResetIRModule
   );

   reg [1:0]         state_outer; // 0 means line following (with IR), 1 means line following (ignore IR until it hits 0), 2 means move servos
   reg [2:0]         state_inner;

   localparam LINE_FOLLOW_IR = 0, LINE_FOLLOW_NO_IR = 1, MOVE_SERVOS = 2;
   localparam FWD = 0, LEFT = 1, RIGHT = 2, BWD = 3, STOP = 4;

   initial 
     begin
        {DutyA,DutyB} <=0;
        EnableIRModule<=0;
        Direction <=0;
        state_outer<=0;
        state_inner<=0;
     end        

   always @ (posedge clk)
     case (state_outer)
       LINE_FOLLOW_IR, LINE_FOLLOW_NO_IR:
         begin
            ResetIRModule<=0;
            if (state_outer == LINE_FOLLOW_IR && IR)
              state_outer <= MOVE_SERVOS;

            else if (state_outer == LINE_FOLLOW_NO_IR && !IR)
              state_outer <= LINE_FOLLOW_IR;

            case (state_inner)
              FWD:
                casex (IPS) 
                  3'b111:     //all sensors detected, stop 
                    begin
                       state_inner <= STOP;
                       Direction <= 4'b0;
                       {DutyA,DutyB} <= {12'd0, 12'd0};
                    end

                  3'b010 :  //middle IPS detected, go straight
                    begin
                       state_inner <= FWD;
                       Direction <= 4'b0110;
                       {DutyA,DutyB} <= {12'd4000, 12'd4000};
                    end

                  3'b1x0: //LEFt or left and middle IPS detected, pivot left
                    begin
                       state_inner <= LEFT;
                       Direction <= 4'b0101;
                       {DutyA,DutyB} <= {12'd3000, 12'd3000};
                    end
                  
                  3'b0x1 : //Right or Right and middle IPS detected, pivot right
                    begin
                       state_inner <= RIGHT;
                       Direction <= 4'b1010;
                       {DutyA,DutyB} <= {12'd3000, 12'd3000};    
                    end

                  default:
                    begin
                       state_inner <= BWD;
                       Direction <= 4'b1001; //Backwards direction to get back on track
                       {DutyA,DutyB} <= {12'd4000,12'd4000};
                    end
                endcase // casex (IPS)

              LEFT:
                casex (IPS) 
                  3'b111:     //all sensors detected, KEEP TURNING LEFT
                    begin
                       state_inner <= LEFT;
                       Direction <= 4'b0101;
                       {DutyA,DutyB} <= {12'd3000, 12'd3000};
                    end

                  3'b010 :  //middle IPS detected, go straight
                    begin
                       state_inner <= FWD;
                       Direction <= 4'b0110;
                       {DutyA,DutyB} <= {12'd4000, 12'd4000};
                    end

                  3'b1x0: //LEFt or left and middle IPS detected, pivot left
                    begin
                       state_inner <= LEFT;
                       Direction <= 4'b0101;
                       {DutyA,DutyB} <= {12'd3000, 12'd3000};
                    end
                  
                  3'b0x1 : //Right or Right and middle IPS detected, pivot right
                    begin
                       state_inner <= RIGHT;
                       Direction <= 4'b1010;
                       {DutyA,DutyB} <= {12'd3000, 12'd3000};    
                    end

                  default:
                    begin
                       state_inner <= LEFT;
                       Direction <= 4'b0101;
                       // state_inner <= BWD;
                       // Direction <= 4'b1001; //Backwards direction to get back on track
                       {DutyA,DutyB} <= {12'd4000,12'd4000};
                    end
                endcase // casex (IPS)

              RIGHT:
                casex (IPS) 
                  3'b111:     //all sensors detected, KEEP TURNING LEFT
                    begin
                       state_inner <= BWD;
                       Direction <= 4'b1001; //Backwards direction to get back on track
                       {DutyA,DutyB} <= {12'd3000, 12'd3000};
                    end

                  3'b010 :  //middle IPS detected, go straight
                    begin
                       state_inner <= FWD;
                       Direction <= 4'b0110;
                       {DutyA,DutyB} <= {12'd4000, 12'd4000};
                    end

                  3'b1x0: //LEFt or left and middle IPS detected, pivot left
                    begin
                       state_inner <= LEFT;
                       Direction <= 4'b0101;
                       {DutyA,DutyB} <= {12'd3000, 12'd3000};
                    end
                  
                  3'b0x1 : //Right or Right and middle IPS detected, pivot right
                    begin
                       state_inner <= RIGHT;
                       Direction <= 4'b1010;
                       {DutyA,DutyB} <= {12'd3000, 12'd3000};    
                    end

                  default:
                    begin
                       state_inner <= RIGHT;
                       Direction <= 4'b1010;
                       // state_inner <= BWD;
                       // Direction <= 4'b1001; //Backwards direction to get back on track
                       {DutyA,DutyB} <= {12'd4000,12'd4000};
                    end
                endcase // casex (IPS)

              BWD:
                casex (IPS) 
                  // 3'b111:     //all sensors detected, KEEP TURNING LEFT
                  //   begin
                  //      state_inner <= RIGHT;
                  //      Direction <= 4'b0101;
                  //      {DutyA,DutyB} <= {12'd3000, 12'd3000};
                  //   end

                  3'b010 :  //middle IPS detected, go straight
                    begin
                       state_inner <= FWD;
                       Direction <= 4'b0110;
                       {DutyA,DutyB} <= {12'd4000, 12'd4000};
                    end

                  3'b1x0: //LEFt or left and middle IPS detected, pivot left
                    begin
                       state_inner <= LEFT;
                       Direction <= 4'b0101;
                       {DutyA,DutyB} <= {12'd3000, 12'd3000};
                    end
                  
                  3'b0x1 : //Right or Right and middle IPS detected, pivot right
                    begin
                       state_inner <= RIGHT;
                       Direction <= 4'b1010;
                       {DutyA,DutyB} <= {12'd3000, 12'd3000};    
                    end

                  default:
                    begin
                       state_inner <= BWD;
                       Direction <= 4'b1001; //Backwards direction to get back on track
                       {DutyA,DutyB} <= {12'd3000, 12'd3000};
                    end
                endcase // casex (IPS)

              default:
                begin
                   state_inner <= STOP;
                   Direction <= 4'b0;
                   {DutyA,DutyB} <= 24'd0;
                end
            endcase // case (state_inner)
         end // case: LINE_FOLLOW_IR, LINE_FOLLOW_NO_IR
       

       MOVE_SERVOS: // State 2 for moving servos
         begin
            Direction <= 4'b0;
            {DutyA,DutyB} <= {12'd0,12'd0};

            // Set enable of IR sensor module
            EnableIRModule <= 1;
            
            if (IRModuleDone)
              begin
                 EnableIRModule <= 0;
                 ResetIRModule <= 1;
                 state_outer <= LINE_FOLLOW_NO_IR;
              end
         end
       
       default: state_outer<=LINE_FOLLOW_IR;
     endcase // case (state_outer)
endmodule

IPSMovement_tb.v
module IPSMovement_tb;

   /*AUTOWIRE*/
   // Beginning of automatic wires (for undeclared instantiated-module outputs)
   wire [3:0]           Direction;              // From uut of IPSMovement.v
   wire [11:0]          DutyA;                  // From uut of IPSMovement.v
   wire [11:0]          DutyB;                  // From uut of IPSMovement.v
   wire                 EnableIRModule;         // From uut of IPSMovement.v
   wire                 ResetIRModule;          // From uut of IPSMovement.v
   // End of automatics
   /*AUTOREGINPUT*/
   // Beginning of automatic reg inputs (for undeclared instantiated-module inputs)
   reg [2:0]            IPS;                    // To uut of IPSMovement.v
   reg                  IR;                     // To uut of IPSMovement.v
   reg                  IRModuleDone;           // To uut of IPSMovement.v
   reg                  clk;                    // To uut of IPSMovement.v
   // End of automatics

   IPSMovement uut
     (/*AUTOINST*/
      // Outputs
      .Direction                        (Direction[3:0]),
      .DutyA                            (DutyA[11:0]),
      .DutyB                            (DutyB[11:0]),
      .EnableIRModule                   (EnableIRModule),
      .ResetIRModule                    (ResetIRModule),
      // Inputs
      .IPS                              (IPS[2:0]),
      .IR                               (IR),
      .IRModuleDone                     (IRModuleDone),
      .clk                              (clk));

   initial
     begin
        $dumpfile("IPSMovement_dmp.vcd");
        $dumpvars(0,IPSMovement_tb);
        IPS<=0;
        IR<=0;
        IRModuleDone<=0;
        clk<=0;
        #1000 $dumpflush;
        $finish;
     end // initial begin

   always #5 clk=~clk;
   always #100 IPS=IPS+1;
   
endmodule

IPSMovement_dmp.vcd
$date
	Mon Dec  2 15:10:44 2019
$end
$version
	Icarus Verilog
$end
$timescale
	1ps
$end
$scope module IPSMovement_tb $end
$var wire 1 ! ResetIRModule $end
$var wire 1 " EnableIRModule $end
$var wire 12 # DutyB [11:0] $end
$var wire 12 $ DutyA [11:0] $end
$var wire 4 % Direction [3:0] $end
$var reg 3 & IPS [2:0] $end
$var reg 1 ' IR $end
$var reg 1 ( IRModuleDone $end
$var reg 1 ) clk $end
$scope module uut $end
$var wire 3 * IPS [2:0] $end
$var wire 1 ' IR $end
$var wire 1 ( IRModuleDone $end
$var wire 1 ) clk $end
$var reg 4 + Direction [3:0] $end
$var reg 12 , DutyA [11:0] $end
$var reg 12 - DutyB [11:0] $end
$var reg 1 " EnableIRModule $end
$var reg 1 ! ResetIRModule $end
$var reg 3 . state_inner [2:0] $end
$var reg 2 / state_outer [1:0] $end
$upscope $end
$upscope $end
$enddefinitions $end
#0
$dumpvars
b0 /
b0 .
b0 -
b0 ,
b0 +
b0 *
0)
0(
0'
b0 &
b0 %
b0 $
b0 #
0"
x!
$end
#5000000000000
b111110100000 $
b111110100000 ,
b111110100000 #
b111110100000 -
b1001 %
b1001 +
b11 .
0!
1)
#10000000000000
0)
#15000000000000
b101110111000 $
b101110111000 ,
b101110111000 #
b101110111000 -
1)
#20000000000000
0)
#25000000000000
1)
#30000000000000
0)
#35000000000000
1)
#40000000000000
0)
#45000000000000
1)
#50000000000000
0)
#55000000000000
1)
#60000000000000
0)
#65000000000000
1)
#70000000000000
0)
#75000000000000
1)
#80000000000000
0)
#85000000000000
1)
#90000000000000
0)
#95000000000000
1)
#100000000000000
0)
b1 &
b1 *
#105000000000000
b1010 %
b1010 +
b10 .
1)
#110000000000000
0)
#115000000000000
1)
#120000000000000
0)
#125000000000000
1)
#130000000000000
0)
#135000000000000
1)
#140000000000000
0)
#145000000000000
1)
#150000000000000
0)
#155000000000000
1)
#160000000000000
0)
#165000000000000
1)
#170000000000000
0)
#175000000000000
1)
#180000000000000
0)
#185000000000000
1)
#190000000000000
0)
#195000000000000
1)
#200000000000000
0)
b10 &
b10 *
#205000000000000
b111110100000 $
b111110100000 ,
b111110100000 #
b111110100000 -
b110 %
b110 +
b0 .
1)
#210000000000000
0)
#215000000000000
1)
#220000000000000
0)
#225000000000000
1)
#230000000000000
0)
#235000000000000
1)
#240000000000000
0)
#245000000000000
1)
#250000000000000
0)
#255000000000000
1)
#260000000000000
0)
#265000000000000
1)
#270000000000000
0)
#275000000000000
1)
#280000000000000
0)
#285000000000000
1)
#290000000000000
0)
#295000000000000
1)
#300000000000000
0)
b11 &
b11 *
#305000000000000
b101110111000 $
b101110111000 ,
b101110111000 #
b101110111000 -
b1010 %
b1010 +
b10 .
1)
#310000000000000
0)
#315000000000000
1)
#320000000000000
0)
#325000000000000
1)
#330000000000000
0)
#335000000000000
1)
#340000000000000
0)
#345000000000000
1)
#350000000000000
0)
#355000000000000
1)
#360000000000000
0)
#365000000000000
1)
#370000000000000
0)
#375000000000000
1)
#380000000000000
0)
#385000000000000
1)
#390000000000000
0)
#395000000000000
1)
#400000000000000
0)
b100 &
b100 *
#405000000000000
b101 %
b101 +
b1 .
1)
#410000000000000
0)
#415000000000000
1)
#420000000000000
0)
#425000000000000
1)
#430000000000000
0)
#435000000000000
1)
#440000000000000
0)
#445000000000000
1)
#450000000000000
0)
#455000000000000
1)
#460000000000000
0)
#465000000000000
1)
#470000000000000
0)
#475000000000000
1)
#480000000000000
0)
#485000000000000
1)
#490000000000000
0)
#495000000000000
1)
#500000000000000
0)
b101 &
b101 *
#505000000000000
b111110100000 $
b111110100000 ,
b111110100000 #
b111110100000 -
1)
#510000000000000
0)
#515000000000000
1)
#520000000000000
0)
#525000000000000
1)
#530000000000000
0)
#535000000000000
1)
#540000000000000
0)
#545000000000000
1)
#550000000000000
0)
#555000000000000
1)
#560000000000000
0)
#565000000000000
1)
#570000000000000
0)
#575000000000000
1)
#580000000000000
0)
#585000000000000
1)
#590000000000000
0)
#595000000000000
1)
#600000000000000
0)
b110 &
b110 *
#605000000000000
b101110111000 $
b101110111000 ,
b101110111000 #
b101110111000 -
1)
#610000000000000
0)
#615000000000000
1)
#620000000000000
0)
#625000000000000
1)
#630000000000000
0)
#635000000000000
1)
#640000000000000
0)
#645000000000000
1)
#650000000000000
0)
#655000000000000
1)
#660000000000000
0)
#665000000000000
1)
#670000000000000
0)
#675000000000000
1)
#680000000000000
0)
#685000000000000
1)
#690000000000000
0)
#695000000000000
1)
#700000000000000
0)
b111 &
b111 *
#705000000000000
1)
#710000000000000
0)
#715000000000000
1)
#720000000000000
0)
#725000000000000
1)
#730000000000000
0)
#735000000000000
1)
#740000000000000
0)
#745000000000000
1)
#750000000000000
0)
#755000000000000
1)
#760000000000000
0)
#765000000000000
1)
#770000000000000
0)
#775000000000000
1)
#780000000000000
0)
#785000000000000
1)
#790000000000000
0)
#795000000000000
1)
#800000000000000
0)
b0 &
b0 *
#805000000000000
b111110100000 $
b111110100000 ,
b111110100000 #
b111110100000 -
1)
#810000000000000
0)
#815000000000000
1)
#820000000000000
0)
#825000000000000
1)
#830000000000000
0)
#835000000000000
1)
#840000000000000
0)
#845000000000000
1)
#850000000000000
0)
#855000000000000
1)
#860000000000000
0)
#865000000000000
1)
#870000000000000
0)
#875000000000000
1)
#880000000000000
0)
#885000000000000
1)
#890000000000000
0)
#895000000000000
1)
#900000000000000
0)
b1 &
b1 *
#905000000000000
b101110111000 $
b101110111000 ,
b101110111000 #
b101110111000 -
b1010 %
b1010 +
b10 .
1)
#910000000000000
0)
#915000000000000
1)
#920000000000000
0)
#925000000000000
1)
#930000000000000
0)
#935000000000000
1)
#940000000000000
0)
#945000000000000
1)
#950000000000000
0)
#955000000000000
1)
#960000000000000
0)
#965000000000000
1)
#970000000000000
0)
#975000000000000
1)
#980000000000000
0)
#985000000000000
1)
#990000000000000
0)
#995000000000000
1)
#1000000000000000
0)
b10 &
b10 *
